{"geocoding":{"version":"0.2","attribution":"https://openrouteservice.org/terms-of-service/#attribution-geocode","query":{"text":"Hotel Watles","size":1,"layers":["venue","street","country","macroregion","region","county","localadmin","locality","borough","neighbourhood","continent","empire","dependency","macrocounty","macrohood","microhood","disputed","postalcode","ocean","marinearea"],"private":false,"lang":{"name":"English","iso6391":"en","iso6393":"eng","via":"default","defaulted":true},"querySize":20,"parser":"pelias","parsed_text":{"subject":"Hotel Watles","venue":"Hotel Watles"}},"warnings":["performance optimization: excluding 'address' layer"],"engine":{"name":"Pelias","author":"Mapzen","version":"1.0"},"timestamp":1623654943347},"type":"FeatureCollection","features":[{"type":"Feature","geometry":{"type":"Point","coordinates":[10.50657,46.701095]},"properties":{"id":"way/153013724","gid":"openstreetmap:venue:way/153013724","layer":"venue","source":"openstreetmap","source_id":"way/153013724","name":"Watles","housenumber":"49","street":"Prämajur - Pramaggiore","postalcode":"39024","confidence":1,"match_type":"exact","accuracy":"point","country":"Italy","country_gid":"whosonfirst:country:85633253","country_a":"ITA","macroregion":"Trentino-Alto Adige/South Tyrol","macroregion_gid":"whosonfirst:macroregion:404227499","region":"Bolzano/Bozen","region_gid":"whosonfirst:region:85685271","region_a":"BZ","localadmin":"Malles Venosta","localadmin_gid":"whosonfirst:localadmin:404473147","continent":"Europe","continent_gid":"whosonfirst:continent:102191581","label":"Watles, Malles Venosta, BZ, Italy","addendum":{"osm":{"operator":"Familie Ziernheld","website":"https://www.watles.com/","phone":"+39 0473 835411"}}},"bbox":[10.5064847,46.700876,10.5073352,46.701422]}],"bbox":[10.5064847,46.700876,10.5073352,46.701422]}